ailab_lite/__init__.py
ailab_lite/_version.py
ailab_lite/node_editor_widget.py
ailab_lite/labextension/package.json
ailab_lite/labextension/static/105.75ea80ad8114cd88beb9.js
ailab_lite/labextension/static/105.75ea80ad8114cd88beb9.js.LICENSE.txt
ailab_lite/labextension/static/144.1169a55af02a732c915a.js
ailab_lite/labextension/static/144.1169a55af02a732c915a.js.LICENSE.txt
ailab_lite/labextension/static/261.1e839b9098b4bd36d77a.js
ailab_lite/labextension/static/261.51b808afa4b9ea5ab4e5.js
ailab_lite/labextension/static/464.3b4e718d0c340b0913c6.js
ailab_lite/labextension/static/464.3b4e718d0c340b0913c6.js.LICENSE.txt
ailab_lite/labextension/static/486.6994c011a634373e59b9.js
ailab_lite/labextension/static/486.6994c011a634373e59b9.js.LICENSE.txt
ailab_lite/labextension/static/568.00a1999b47481ad81312.js
ailab_lite/labextension/static/568.077af8d3ba7b7e25e388.js
ailab_lite/labextension/static/568.11c4d744f132c77961a4.js
ailab_lite/labextension/static/568.28d3fd05a894a8650902.js
ailab_lite/labextension/static/568.377ffe64696a73aa6c51.js
ailab_lite/labextension/static/568.571ea73ef7118a8d9c40.js
ailab_lite/labextension/static/568.588f69486cfecd8887c4.js
ailab_lite/labextension/static/568.5abefcd945d425ee2053.js
ailab_lite/labextension/static/568.5b45396997bc046e6c35.js
ailab_lite/labextension/static/568.5e169f0576b9ae62ed0b.js
ailab_lite/labextension/static/568.62103585cd0273efe6e8.js
ailab_lite/labextension/static/568.668570e4d54c29e35a17.js
ailab_lite/labextension/static/568.822926b776cdc3ae237d.js
ailab_lite/labextension/static/568.95880248d4583fbdcacb.js
ailab_lite/labextension/static/568.a883ed03086afaa334ca.js
ailab_lite/labextension/static/568.cc864daa5babc0a9ffb1.js
ailab_lite/labextension/static/568.d10d42a2dde3b82cd3ae.js
ailab_lite/labextension/static/940.fe6b2b9a2a1397d6d4ce.js
ailab_lite/labextension/static/940.fe6b2b9a2a1397d6d4ce.js.LICENSE.txt
ailab_lite/labextension/static/remoteEntry.289aa88cd12e0b26719c.js
ailab_lite-0.1.14.dist-info/METADATA
ailab_lite-0.1.14.dist-info/WHEEL
ailab_lite-0.1.14.dist-info/top_level.txt
ailab_lite-0.1.14.dist-info/RECORD
